CONTRIBUTORS.rst
MANIFEST.in
README.rst
setup.cfg
setup.py
docs/HISTORY.rst
docs/INSTALL.txt
docs/LICENSE.txt
fez/__init__.py
fez.atcsv.egg-info/PKG-INFO
fez.atcsv.egg-info/SOURCES.txt
fez.atcsv.egg-info/dependency_links.txt
fez.atcsv.egg-info/entry_points.txt
fez.atcsv.egg-info/namespace_packages.txt
fez.atcsv.egg-info/not-zip-safe
fez.atcsv.egg-info/paster_plugins.txt
fez.atcsv.egg-info/requires.txt
fez.atcsv.egg-info/top_level.txt
fez/atcsv/README.rst
fez/atcsv/__init__.py
fez/atcsv/config.py
fez/atcsv/configure.zcml
fez/atcsv/importer.py
fez/atcsv/interfaces.py
fez/atcsv/tests.py
fez/atcsv/vocabularies.py
fez/atcsv/browser/__init__.py
fez/atcsv/browser/configure.zcml
fez/atcsv/browser/forms.py
fez/atcsv/profiles/default/actions.xml
fez/atcsv/profiles/default/metadata.xml
fez/atcsv/profiles/default/portlets.xml
