Metadata-Version: 1.0
Name: fez.atcsv
Version: 0.2
Summary: Simple AT CSV processing
Home-page: http://www.fezconsulting.com
Author: Dan Fairs
Author-email: dan@fezconsulting.com
License: BSD
Keywords: plone zope archetypes csv import
Platform: UNKNOWN
Classifier: Framework :: Plone
Classifier: Intended Audience :: Developers
Classifier: Topic :: Software Development :: Libraries :: Python Modules
Classifier: License :: OSI Approved :: BSD License
Classifier: Development Status :: 3 - Alpha
